<?xml version="1.0" encoding="utf-8"?>
<resources>
    <color name="background">@*android:color/background_dark</color>
    <color name="copydrop_overlay_bg">@*android:color/background_floating_material_dark</color>
    <color name="copydrop_text">@*android:color/white</color>
    <color name="copydrop_welcome_notice_bg">@*android:color/background_floating_material_dark</color>
    <color name="disabled_content">#61ffffff</color>
    <color name="disabled_fill">@*android:color/background_dark</color>
    <color name="hairline">@*android:color/white</color>
    <color name="icon_primary_dark">#ff1976d2</color>
    <color name="listen_high_light_color">#591976d2</color>
    <color name="listen_intro_title_text_color">@*android:color/white</color>
    <color name="on_surface">@*android:color/white</color>
    <color name="primary_blue">#ff1976d2</color>
    <color name="primary_blue_dark">#ff0d47a1</color>
    <color name="surface">@*android:color/background_floating_material_dark</color>
</resources>
