<?xml version="1.0" encoding="utf-8"?>
<resources>
    <color name="common_account_chip_account_subtitle_day_night_color">@*android:color/secondary_text_default_material_dark</color>
    <color name="common_account_chip_account_title_day_night_color">@*android:color/white</color>
    <color name="common_account_consent_day_night_color">@*android:color/secondary_text_default_material_dark</color>
    <color name="common_account_divider_day_night_color">@*android:color/transparent</color>
    <color name="common_account_link_day_night_color">#ff1976d2</color>
    <color name="common_account_main_title_day_night_color">@*android:color/white</color>
    <color name="tp_action_text_color">#ff1976d2</color>
    <color name="tp_bad">#ffd32f2f</color>
    <color name="tp_dismiss_button_tint_color">@*android:color/white</color>
    <color name="tp_divider_color">@*android:color/transparent</color>
    <color name="tp_logo_border_color">#ffffffff</color>
    <color name="tp_logo_fill_color">#ffffffff</color>
    <color name="tp_logo_letter_color">#ffffffff</color>
    <color name="tp_primary_text_color">@*android:color/white</color>
    <color name="tp_radio_button_color">#ff1976d2</color>
    <color name="tp_secondary_text_color">@*android:color/secondary_text_default_material_dark</color>
    <color name="tp_settings_text_color">#ff1976d2</color>
</resources>
