<?xml version="1.0" encoding="utf-8"?>
<resources>
    <style name="Base.V14.Theme.GoogleMaterial.Light" parent="@*com.google.android.gm:style/Base.V14.Theme.GoogleMaterial.Light.Bridge">
        <item name="android:colorBackground">@*com.google.android.gm:color/google_default_color_background</item>
        <item name="android:windowBackground">@*com.google.android.gm:color/google_default_color_background</item>
        <item name="android:timePickerDialogTheme">@*com.google.android.gm:style/ThemeOverlay.GoogleMaterial.Dialog</item>
        <item name="android:datePickerDialogTheme">@*com.google.android.gm:style/ThemeOverlay.GoogleMaterial.Dialog</item>
        <item name="android:colorEdgeEffect">@*android:color/secondary_text_default_material_dark</item>
        <item name="android:windowLightStatusBar">false</item>
        <item name="*com.google.android.gm:bottomAppBarStyle">@*com.google.android.gm:style/Widget.GoogleMaterial.BottomAppBar</item>
        <item name="*com.google.android.gm:bottomNavigationStyle">@*com.google.android.gm:style/Widget.GoogleMaterial.BottomNavigationView</item>
        <item name="*com.google.android.gm:bottomSheetDialogTheme">@*com.google.android.gm:style/Theme.GoogleMaterial.Light.BottomSheetDialog</item>
        <item name="*com.google.android.gm:chipGroupStyle">@*com.google.android.gm:style/Widget.GoogleMaterial.ChipGroup</item>
        <item name="*com.google.android.gm:chipStandaloneStyle">@*com.google.android.gm:style/Widget.GoogleMaterial.Chip.Input</item>
        <item name="*com.google.android.gm:chipStyle">@*com.google.android.gm:style/Widget.GoogleMaterial.Chip.Assistive</item>
        <item name="*com.google.android.gm:extendedFloatingActionButtonStyle">@*com.google.android.gm:style/Widget.GoogleMaterial.ExtendedFloatingActionButton.Icon</item>
        <item name="*com.google.android.gm:floatingActionButtonStyle">@*com.google.android.gm:style/Widget.GoogleMaterial.FloatingActionButton</item>
        <item name="*com.google.android.gm:materialButtonStyle">@*com.google.android.gm:style/Widget.GoogleMaterial.Button</item>
        <item name="*com.google.android.gm:materialCardViewStyle">@*com.google.android.gm:style/Widget.GoogleMaterial.CardView</item>
        <item name="*com.google.android.gm:navigationViewStyle">@*com.google.android.gm:style/Widget.GoogleMaterial.NavigationView</item>
        <item name="*com.google.android.gm:openSearchBarStyle">@*com.google.android.gm:style/Widget.GoogleMaterial.OpenSearchBar</item>
        <item name="*com.google.android.gm:openSearchViewPrefixStyle">@*com.google.android.gm:style/Widget.GoogleMaterial.OpenSearchView.Prefix</item>
        <item name="*com.google.android.gm:openSearchViewStyle">@*com.google.android.gm:style/Widget.GoogleMaterial.OpenSearchView</item>
        <item name="*com.google.android.gm:productLockupViewStyle">@*com.google.android.gm:style/Widget.GoogleMaterial.ProductLockupView</item>
        <item name="*com.google.android.gm:tabStyle">@*com.google.android.gm:style/Widget.GoogleMaterial.TabLayout</item>
        <item name="*com.google.android.gm:textInputStyle">@*com.google.android.gm:style/Widget.GoogleMaterial.TextInputLayout.OutlinedBox</item>
        <item name="*com.google.android.gm:actionOverflowMenuStyle">@*com.google.android.gm:style/Widget.GoogleMaterial.PopupMenu.Overflow</item>
        <item name="*com.google.android.gm:actionBarStyle">@*com.google.android.gm:style/Widget.GoogleMaterial.Light.ActionBar.Solid</item>
        <item name="*com.google.android.gm:borderlessButtonStyle">@*com.google.android.gm:style/Widget.GoogleMaterial.TextButton</item>
        <item name="*com.google.android.gm:toolbarStyle">@*com.google.android.gm:style/Widget.GoogleMaterial.Toolbar</item>
        <item name="*com.google.android.gm:popupMenuStyle">@*com.google.android.gm:style/Widget.GoogleMaterial.PopupMenu</item>
        <item name="*com.google.android.gm:colorPrimary">@*com.google.android.gm:color/google_default_color_primary</item>
        <item name="*com.google.android.gm:colorPrimaryDark">@*com.google.android.gm:color/google_default_color_primary_dark</item>
        <item name="*com.google.android.gm:colorAccent">@*com.google.android.gm:color/google_blue600</item>
        <item name="*com.google.android.gm:alertDialogTheme">@*com.google.android.gm:style/ThemeOverlay.GoogleMaterial.Dialog.Alert</item>
        <item name="*com.google.android.gm:buttonStyle">@*com.google.android.gm:style/Widget.AppCompat.Button.Colored</item>
        <item name="*com.google.android.gm:checkboxStyle">@*com.google.android.gm:style/Widget.GoogleMaterial.CompoundButton.CheckBox</item>
        <item name="*com.google.android.gm:radioButtonStyle">@*com.google.android.gm:style/Widget.GoogleMaterial.CompoundButton.RadioButton</item>
        <item name="*com.google.android.gm:switchStyle">@*com.google.android.gm:style/Widget.GoogleMaterial.CompoundButton.Switch</item>
        <item name="*com.google.android.gm:colorError">@*com.google.android.gm:color/google_default_color_error</item>
        <item name="*com.google.android.gm:viewInflaterClass">android.support.design.theme.MaterialComponentsViewInflater</item>
        <item name="*com.google.android.gm:materialAlertDialogTheme">@*com.google.android.gm:style/ThemeOverlay.GoogleMaterial.MaterialAlertDialog</item>
        <item name="*com.google.android.gm:snackbarStyle">@*com.google.android.gm:style/Widget.GoogleMaterial.Snackbar</item>
        <item name="*com.google.android.gm:snackbarButtonStyle">@*com.google.android.gm:style/Widget.GoogleMaterial.TextButton.Snackbar</item>
    </style>
    <style name="ColoredNavBarGeneralTheme" parent="@*com.google.android.gm:style/BaseGeneralTheme">
        <item name="android:navigationBarColor">@*android:color/primary_dark_material_dark</item>
    </style>
    <style name="ColoredNavBarMailActivityTheme" parent="@*com.google.android.gm:style/BaseMailActivityTheme">
        <item name="android:navigationBarColor">@*android:color/primary_dark_material_dark</item>
    </style>
    <style name="ComposeThemeBase" parent="@*com.google.android.gm:style/ColoredNavBarGeneralTheme">
        <item name="android:colorBackground">@*android:color/background_dark</item>
        <item name="android:windowBackground">@*android:color/background_dark</item>
        <item name="android:dropDownListViewStyle">@*com.google.android.gm:style/ComposeDropdownListViewStyle</item>
        <item name="android:colorBackgroundCacheHint">@*android:color/background_dark</item>
        <item name="android:windowDrawsSystemBarBackgrounds">true</item>
        <item name="*com.google.android.gm:popupMenuStyle">@*com.google.android.gm:style/PopupMenu</item>
    </style>
    <style name="SuwThemeGlifV2.Light" parent="@*com.google.android.gm:style/SuwThemeGlif.Light">
        <item name="android:colorBackground">@*com.google.android.gm:color/suw_glif_background_color_light</item>
        <item name="android:editTextStyle">@*com.google.android.gm:style/SuwEditText</item>
        <item name="android:alertDialogTheme">@*com.google.android.gm:style/SuwAlertDialogTheme.Light</item>
        <item name="android:windowLightStatusBar">false</item>
        <item name="*com.google.android.gm:suwDividerInsetEnd">@*com.google.android.gm:dimen/suw_layout_margin_sides</item>
        <item name="*com.google.android.gm:suwDividerInsetStart">@*com.google.android.gm:dimen/suw_layout_margin_sides</item>
        <item name="*com.google.android.gm:suwDividerInsetStartNoIcon">@*com.google.android.gm:dimen/suw_layout_margin_sides</item>
        <item name="*com.google.android.gm:suwEditTextBackgroundColor">@*com.google.android.gm:color/suw_glif_edit_text_bg_light_color</item>
        <item name="*com.google.android.gm:suwGlifHeaderGravity">center_horizontal</item>
        <item name="*com.google.android.gm:suwScrollIndicators">bottom|top</item>
        <item name="*com.google.android.gm:suwBackgroundPatterned">false</item>
        <item name="*com.google.android.gm:suwBackgroundBaseColor">@*android:color/background_floating_material_dark</item>
    </style>
</resources>
