<?xml version="1.0" encoding="utf-8"?>
<layer-list
  xmlns:android="http://schemas.android.com/apk/res/android">
    <item>
        <shape android:shape="rectangle">
            <corners android:radius="@*com.google.android.apps.chromecast.app:dimen/circle_outline_grey_radius" />
            <stroke android:width="@*com.google.android.apps.chromecast.app:dimen/circle_outline_grey_stroke_width" android:color="@*android:color/white" />
        </shape>
    </item>
    <item>
        <ripple android:color="@*android:color/ripple_material_dark">
            <item android:id="@*android:id/mask">
                <shape android:shape="rectangle">
                    <corners android:radius="@*com.google.android.apps.chromecast.app:dimen/circle_outline_grey_radius" />
                    <solid android:color="@*android:color/white" />
                </shape>
            </item>
        </ripple>
    </item>
</layer-list>
