<?xml version="1.0" encoding="utf-8"?>
<vector android:height="40.0dip" android:width="40.0dip" android:viewportWidth="120.0" android:viewportHeight="120.0"
  xmlns:android="http://schemas.android.com/apk/res/android">
    <group android:translateX="-48.0" android:translateY="-504.0">
        <group android:translateX="48.0" android:translateY="504.0">
            <path android:fillColor="@*android:color/button_material_dark" android:pathData="M 60 0 C 93.1370849898 0 120 26.8629150102 120 60 C 120 93.1370849898 93.1370849898 120 60 120 C 26.8629150102 120 0 93.1370849898 0 60 C 0 26.8629150102 26.8629150102 0 60 0 Z" android:strokeWidth="1.0" />
            <group android:translateX="24.0" android:translateY="26.0">
                <path android:fillColor="#ffffffff" android:pathData="M34.5,31.5 C41.13,31.5 46.5,26.13 46.5,19.5 C46.5,12.87 41.13,7.5 34.5,7.5 C27.87,7.5 22.5,12.87 22.5,19.5 C22.5,26.13 27.87,31.5 34.5,31.5 L34.5,31.5 Z M34.5,37.5 C26.49,37.5 10.5,41.52 10.5,49.5 L10.5,55.5 L58.5,55.5 L58.5,49.5 C58.5,41.52 42.51,37.5 34.5,37.5 L34.5,37.5 Z" android:strokeWidth="1.0" />
                <path android:pathData="M 0 0 L 72 0 L 72 72 L 0 72 Z" android:strokeWidth="1.0" />
            </group>
        </group>
    </group>
</vector>
