<?xml version="1.0" encoding="utf-8"?>
<resources>
    <color name="cardview_dark_background">@*android:color/background_floating_material_dark</color>
    <color name="cardview_light_background">@*android:color/background_floating_material_dark</color>
    <color name="material_grey_800">@*android:color/background_floating_material_dark</color>
    <dimen name="actionbar_contentInsetStart">10.0dip</dimen>
    <dimen name="dashboard_padding_bottom">10.0dip</dimen>
    <dimen name="dashboard_padding_end">21.0dip</dimen>
    <dimen name="dashboard_padding_start">21.0dip</dimen>
    <dimen name="dashboard_padding_top">10.0dip</dimen>
    <dimen name="divider_height">0.0dip</dimen>
    <dimen name="divider_margin_bottom">0.0dip</dimen>
    <dimen name="divider_margin_top">0.0dip</dimen>
</resources>
