<?xml version="1.0" encoding="utf-8"?>
<resources>
    <style name="Base.TextAppearance.AppCompat.Inverse" parent="@*android:style/TextAppearance.Material" />
    <style name="Base.TextAppearance.AppCompat.Large.Inverse" parent="@*android:style/TextAppearance.Material.Large" />
    <style name="Base.TextAppearance.AppCompat.Medium.Inverse" parent="@*android:style/TextAppearance.Material.Medium" />
    <style name="Base.TextAppearance.AppCompat.Small.Inverse" parent="@*android:style/TextAppearance.Material.Small" />
    <style name="Base.Widget.AppCompat.Light.ActionBar.TabText" parent="@*android:style/Widget.Material.ActionBar.TabText" />
    <style name="Base.Widget.AppCompat.Light.ActionBar.TabText.Inverse" parent="@*android:style/Widget.Material.ActionBar.TabText" />
    <style name="Base.Widget.AppCompat.Light.ActionBar.TabView" parent="@*android:style/Widget.Material.ActionBar.TabView" />
    <style name="Base.Widget.AppCompat.Light.PopupMenu" parent="@*android:style/Widget.Material.PopupMenu" />
    <style name="Platform.V21.AppCompat.Light" parent="@*android:style/Theme.Material.NoActionBar">
        <item name="android:textColorHintInverse">#ffbbbbbb</item>
        <item name="android:textColorHint">#ffbbbbbb</item>
        <item name="android:textColorLink">@*android:color/accent_material_dark</item>
        <item name="android:textColorLinkInverse">@*android:color/accent_material_dark</item>
    </style>
    <style name="reminders_activity" parent="@*android:style/Theme.Material.NoActionBar">
        <item name="android:colorPrimaryDark">#ff0d47a1</item>
    </style>
    <style name="Theme.SearchNow" parent="@*com.google.android.googlequicksearchbox:style/Theme.Velvet">
        <item name="android:statusBarColor">@*android:color/transparent</item>
        <item name="android:backgroundTint">@*android:color/background_dark</item>
    </style>
    <style name="Theme.Shim.Light" parent="@*android:style/Theme.DeviceDefault.Light" />
    <style name="Theme.Shim.Light.Dialog" parent="@*android:style/Theme.Material.Dialog" />
    <style name="Theme.Shim.Light.NoActionBar" parent="@*android:style/Theme.Material.NoActionBar" />
    <style name="Theme_Holo_Light_Dialog_Alert" parent="@*android:style/Theme.Holo.Dialog">
        <item name="android:windowBackground">@*android:color/transparent</item>
        <item name="android:windowContentOverlay">@null</item>
        <item name="android:windowMinWidthMajor">@*android:dimen/dialog_min_width_major</item>
        <item name="android:windowMinWidthMinor">@*android:dimen/dialog_min_width_minor</item>
    </style>
    <style name="UrawTheme" parent="@*android:style/Theme.DeviceDefault.Light">
        <item name="android:colorControlActivated">@*com.google.android.googlequicksearchbox:color/quantum_googblue500</item>
    </style>
    <style name="Widget.Shim.Light.ActionBar" parent="@*android:style/Widget.Material.ActionBar" />
</resources>
