<?xml version="1.0" encoding="utf-8"?>
<layer-list
  xmlns:android="http://schemas.android.com/apk/res/android">
    <item>
        <shape android:shape="oval">
            <solid android:color="@*com.google.android.apps.googlevoice:color/quantum_googblue" />
        </shape>
    </item>
    <item android:left="4.0dip" android:top="4.0dip" android:right="4.0dip" android:bottom="4.0dip">
        <shape android:shape="oval">
            <solid android:color="@*android:color/button_material_dark" />
        </shape>
    </item>
    <item android:left="10.0dip" android:top="10.0dip" android:right="10.0dip" android:bottom="10.0dip">
        <bitmap android:gravity="center" android:src="@*com.google.android.apps.googlevoice:drawable/quantum_ic_add_googblue_48" />
    </item>
</layer-list>
