<?xml version="1.0" encoding="utf-8"?>
<resources>
    <style name="MainTheme" parent="@*com.android.chrome:style/MainThemeBase">
        <item name="android:navigationBarColor">@*com.android.chrome:color/bottom_system_nav_color</item>
        <item name="android:windowLightNavigationBar">false</item>
    </style>
    <style name="FullscreenWhite" parent="@*com.android.chrome:style/FullscreenWhiteBase">
        <item name="android:navigationBarColor">@*com.android.chrome:color/bottom_system_nav_color</item>
        <item name="android:windowLightNavigationBar">false</item>
    </style>
    <style name="ThemeWithActionBar" parent="@*com.android.chrome:style/ThemeWithActionBarBase">
        <item name="android:navigationBarColor">@*com.android.chrome:color/bottom_system_nav_color</item>
        <item name="android:windowLightNavigationBar">false</item>
    </style>
    <style name="DialogWhenLarge" parent="@*com.android.chrome:style/DialogWhenLargeBase">
        <item name="android:navigationBarColor">@*com.android.chrome:color/bottom_system_nav_color</item>
        <item name="android:windowLightNavigationBar">false</item>
    </style>
</resources>
