<?xml version="1.0" encoding="utf-8"?>
<resources>
    <style name="AppTheme.SolidStatusBarBase" parent="@*com.google.android.apps.chromecast.app:style/AppTheme">
        <item name="android:windowTranslucentStatus">false</item>
        <item name="android:windowDrawsSystemBarBackgrounds">true</item>
        <item name="android:statusBarColor">@*android:color/primary_dark_material_dark</item>
        <item name="android:navigationBarColor">@*android:color/primary_dark_material_dark</item>
        <item name="android:windowLightStatusBar">false</item>
        <item name="android:windowLightNavigationBar">false</item>
        <item name="android:navigationBarDividerColor">@*android:color/primary_dark_material_dark</item>
        <item name="*com.google.android.apps.chromecast.app:colorPrimaryDark">@*android:color/primary_dark_material_dark</item>
        <item name="*com.google.android.apps.chromecast.app:windowActionBar">false</item>
    </style>
</resources>
